{
  "_class": "shapeGroup",
  "clippingMaskMode": 0,
  "do_objectID": "0B73B66D-93B3-408C-B93C-63BD4ABCD145",
  "exportOptions": {
    "_class": "exportOptions",
    "exportFormats": [
    ],
    "includedLayerIds": [
    ],
    "layerOptions": 0,
    "shouldTrim": false
  },
  "frame": {
    "_class": "rect",
    "constrainProportions": true,
    "height": 4,
    "width": 4,
    "x": 1375,
    "y": 300
  },
  "hasClickThrough": false,
  "hasClippingMask": false,
  "isFlippedHorizontal": false,
  "isFlippedVertical": false,
  "isLocked": false,
  "isVisible": true,
  "layerListExpandedType": 0,
  "layers": [
    {
      "class": "oval",
      "id": "69092895-0A3F-44C7-AB5D-CA9180276B48"
    }
  ],
  "name": "Oval 2",
  "nameIsFixed": false,
  "resizingConstraint": 63,
  "resizingType": 0,
  "rotation": 0,
  "shouldBreakMaskChain": false,
  "style": {
    "_class": "style",
    "endDecorationType": 0,
    "fills": [
      {
        "_class": "fill",
        "color": {
          "_class": "color",
          "alpha": 1,
          "blue": 0.1529411764705882,
          "green": 0.1843137254901961,
          "red": 0.1411764705882353
        },
        "fillType": 0,
        "isEnabled": true,
        "noiseIndex": 0,
        "noiseIntensity": 0,
        "patternFillType": 1,
        "patternTileScale": 1
      }
    ],
    "miterLimit": 10,
    "startDecorationType": 0
  },
  "userInfo": {
    "com.animaapp.stc-sketch-plugin": {
      "kModelPropertiesKey": {
        "constraints": {
          "aspectRatio": {
            "constant": 4,
            "enabled": 1,
            "modelID": "constraint_2e6ac9b5-e582-4035-831c-712260341c14",
            "model_class": "ADModelConstraint",
            "model_version": 0.1,
            "multiplier": 4
          },
          "automatic": 1,
          "modelID": "viewConstraints_1d9b39aa-60e9-4191-88a1-9f43cbfc1326",
          "model_class": "ADModelViewConstraints",
          "model_version": 0.1,
          "scaleFactor": 1
        }
      }
    }
  },
  "windingRule": 1
}