{
  "_class": "shapeGroup",
  "clippingMaskMode": 0,
  "do_objectID": "01985F4A-EF99-493C-8D39-052115A69371",
  "exportOptions": {
    "_class": "exportOptions",
    "exportFormats": [
    ],
    "includedLayerIds": [
    ],
    "layerOptions": 0,
    "shouldTrim": false
  },
  "frame": {
    "_class": "rect",
    "constrainProportions": true,
    "height": 4,
    "width": 4,
    "x": 40,
    "y": 275
  },
  "hasClickThrough": false,
  "hasClippingMask": false,
  "isFlippedHorizontal": false,
  "isFlippedVertical": false,
  "isLocked": false,
  "isVisible": true,
  "layerListExpandedType": 0,
  "layers": [
    {
      "class": "oval",
      "id": "63D34889-E68C-49D4-A553-CDA990658EBA"
    }
  ],
  "name": "Oval 2",
  "nameIsFixed": false,
  "resizingConstraint": 63,
  "resizingType": 0,
  "rotation": 0,
  "shouldBreakMaskChain": false,
  "style": {
    "_class": "style",
    "endDecorationType": 0,
    "fills": [
      {
        "_class": "fill",
        "color": {
          "_class": "color",
          "alpha": 1,
          "blue": 0.1529411764705882,
          "green": 0.1843137254901961,
          "red": 0.1411764705882353
        },
        "fillType": 0,
        "isEnabled": true,
        "noiseIndex": 0,
        "noiseIntensity": 0,
        "patternFillType": 1,
        "patternTileScale": 1
      }
    ],
    "miterLimit": 10,
    "startDecorationType": 0
  },
  "userInfo": {
    "com.animaapp.stc-sketch-plugin": {
      "kModelPropertiesKey": {
        "constraints": {
          "aspectRatio": {
            "constant": 4,
            "enabled": 1,
            "modelID": "constraint_1e52e56b-747c-4ab0-971f-3e6fc953adde",
            "model_class": "ADModelConstraint",
            "model_version": 0.1,
            "multiplier": 4
          },
          "automatic": 1,
          "modelID": "viewConstraints_c1fb75a1-a47f-4ae3-bdf8-52fa15296778",
          "model_class": "ADModelViewConstraints",
          "model_version": 0.1,
          "scaleFactor": 1
        }
      }
    }
  },
  "windingRule": 1
}